{
  "name": "Tc001",
  "options": {
    "idInjection": false,
    "mssql": {
      "schema": "dbo",
      "table": "TC001"
    }
  },
  "properties": {
    "canumi": {
      "type": "Number",
      "required": true,
      "length": null,
      "precision": 10,
      "scale": 0,
      "id": 1,
      "generated": false,
      "mssql": {
        "columnName": "canumi",
        "dataType": "int",
        "dataLength": null,
        "dataPrecision": 10,
        "dataScale": 0,
        "nullable": "NO"
      }
    },
    "cacod": {
      "type": "String",
      "required": false,
      "length": 10,
      "precision": null,
      "scale": null,
      "mssql": {
        "columnName": "cacod",
        "dataType": "nvarchar",
        "dataLength": 10,
        "dataPrecision": null,
        "dataScale": null,
        "nullable": "YES"
      }
    },
    "cadesc": {
      "type": "String",
      "required": false,
      "length": 30,
      "precision": null,
      "scale": null,
      "mssql": {
        "columnName": "cadesc",
        "dataType": "nvarchar",
        "dataLength": 30,
        "dataPrecision": null,
        "dataScale": null,
        "nullable": "YES"
      }
    },
    "cadesc2": {
      "type": "String",
      "required": false,
      "length": 15,
      "precision": null,
      "scale": null,
      "mssql": {
        "columnName": "cadesc2",
        "dataType": "nvarchar",
        "dataLength": 15,
        "dataPrecision": null,
        "dataScale": null,
        "nullable": "YES"
      }
    },
    "cacat": {
      "type": "Number",
      "required": false,
      "length": null,
      "precision": 10,
      "scale": 0,
      "mssql": {
        "columnName": "cacat",
        "dataType": "int",
        "dataLength": null,
        "dataPrecision": 10,
        "dataScale": 0,
        "nullable": "YES"
      }
    },
    "caimg": {
      "type": "String",
      "required": false,
      "length": 30,
      "precision": null,
      "scale": null,
      "mssql": {
        "columnName": "caimg",
        "dataType": "nvarchar",
        "dataLength": 30,
        "dataPrecision": null,
        "dataScale": null,
        "nullable": "YES"
      }
    },
    "castc": {
      "type": "Boolean",
      "required": false,
      "length": null,
      "precision": null,
      "scale": null,
      "mssql": {
        "columnName": "castc",
        "dataType": "bit",
        "dataLength": null,
        "dataPrecision": null,
        "dataScale": null,
        "nullable": "YES"
      }
    },
    "caest": {
      "type": "Boolean",
      "required": false,
      "length": null,
      "precision": null,
      "scale": null,
      "mssql": {
        "columnName": "caest",
        "dataType": "bit",
        "dataLength": null,
        "dataPrecision": null,
        "dataScale": null,
        "nullable": "YES"
      }
    },
    "caserie": {
      "type": "Boolean",
      "required": false,
      "length": null,
      "precision": null,
      "scale": null,
      "mssql": {
        "columnName": "caserie",
        "dataType": "bit",
        "dataLength": null,
        "dataPrecision": null,
        "dataScale": null,
        "nullable": "YES"
      }
    },
    "cafact": {
      "type": "Date",
      "required": false,
      "length": null,
      "precision": null,
      "scale": null,
      "mssql": {
        "columnName": "cafact",
        "dataType": "date",
        "dataLength": null,
        "dataPrecision": null,
        "dataScale": null,
        "nullable": "YES"
      }
    },
    "cahact": {
      "type": "String",
      "required": false,
      "length": 5,
      "precision": null,
      "scale": null,
      "mssql": {
        "columnName": "cahact",
        "dataType": "nvarchar",
        "dataLength": 5,
        "dataPrecision": null,
        "dataScale": null,
        "nullable": "YES"
      }
    },
    "cauact": {
      "type": "String",
      "required": false,
      "length": 10,
      "precision": null,
      "scale": null,
      "mssql": {
        "columnName": "cauact",
        "dataType": "nvarchar",
        "dataLength": 10,
        "dataPrecision": null,
        "dataScale": null,
        "nullable": "YES"
      }
    }
  }
}
